checkpatch_junit/__init__.py
checkpatch_junit-0.0.1.dist-info/LICENSE
checkpatch_junit-0.0.1.dist-info/METADATA
checkpatch_junit-0.0.1.dist-info/WHEEL
checkpatch_junit-0.0.1.dist-info/entry_points.txt
checkpatch_junit-0.0.1.dist-info/top_level.txt
checkpatch_junit-0.0.1.dist-info/RECORD
