Metadata-Version: 2.1
Name: checkpatch-junit
Version: 0.0.1
Summary: Provide JUnit output to Linux checkpatch.pl script
Home-page: https://github.com/mastiggia/checkpatch-junit
Author: Mastiggia
Author-email: mastiggia@gmail.com
License: GPLv3
Keywords: checkpatch,ci,junit
Platform: UNKNOWN
Classifier: Development Status :: 3 - Alpha
Classifier: Environment :: Console
Classifier: Intended Audience :: Developers
Classifier: License :: OSI Approved :: GNU General Public License v3 (GPLv3)
Classifier: Operating System :: POSIX :: Linux
Classifier: Programming Language :: Python :: 3 :: Only
Classifier: Topic :: Software Development :: Testing :: Unit
Requires-Python: >=3.6, <4
License-File: LICENSE
Requires-Dist: junit-xml (>=1.9)
